Metadata-Version: 2.1
Name: scpi-protocol
Version: 0.1.4
Summary: Sans I/O SCPI protocol parser
Home-page: https://gitlab.com/tiagocoutinho/scpi-protocol/
Author: Jose Tiago Macara Coutinho
Author-email: coutinhotiago@gmail.com
License: GPLv3+
Keywords: SCPI,parser
Platform: UNKNOWN
Classifier: Development Status :: 2 - Pre-Alpha
Classifier: Intended Audience :: Developers
Classifier: Natural Language :: English
Classifier: Programming Language :: Python :: 3
Classifier: Programming Language :: Python :: 3.5
Classifier: Programming Language :: Python :: 3.6
Classifier: Programming Language :: Python :: 3.7
Requires-Python: >=3.5
